simple_mcp/__init__.py
simple_mcp/simple_mcp.py
simple_mcp-0.1.1.dist-info/METADATA
simple_mcp-0.1.1.dist-info/WHEEL
simple_mcp-0.1.1.dist-info/entry_points.txt
simple_mcp-0.1.1.dist-info/licenses/LICENSE
simple_mcp-0.1.1.dist-info/RECORD
