Metadata-Version: 2.4
Name: simple-mcp
Version: 0.1.1
Summary: A simple demonstration of the Model Context Protocol (MCP) implementation
Author-email: Arunkumar Selvam <arunkse@amazon.com>
License-File: LICENSE
Classifier: License :: OSI Approved :: MIT License
Classifier: Operating System :: OS Independent
Classifier: Programming Language :: Python :: 3
Requires-Python: >=3.12
Requires-Dist: build>=1.2.2.post1
Requires-Dist: mcp[cli]>=1.9.2
Requires-Dist: twine>=6.1.0
